[
    {
        "name": "communities",
        "display_name": "Communities",
        "model_name": "Community",
        "source": "internal",
        "source_type": "csv",
        "source_file_path": "data/COMMUNITIES_V6.csv",
        "import_order": 9
    },
    {
        "name": "first_responders",
        "display_name": "First Responders",
        "model_name": "FirstResponder",
        "source": "databc",
        "source_type": "WMS",
        "resource_id": "70899feb-b62f-4cd0-aeff-32e1936c3018",
        "permalink_id": "652c49eb-7295-4ae2-8f26-39103f23b50d",
        "dataset": "first-responders",
        "import_order": 10
    },
    {
        "name": "diagnostic_facilities",
        "display_name": "Diagnostic Facilities",
        "model_name": "DiagnosticFacility",
        "source": "databc",
        "source_type": "WMS",
        "resource_id": "e546be7a-a432-458b-91a0-1084887c291c",
        "permalink_id": "4f75e9f6-1459-4ae2-990d-b53b1c389525",
        "dataset": "diagnostic-facilities",
        "import_order": 11
    },
    {
        "name": "timber_facilities",
        "display_name": "Timber Facilities",
        "model_name": "TimberFacility",
        "source": "databc",
        "source_type": "WMS",
        "resource_id": "c5553f20-f589-4ca5-8ed6-afb45ae281b1",
        "permalink_id": "67daf53d-e3bb-45ee-9121-8aa1193b7492",
        "dataset": "british-columbia-major-timber-processing-facilities",
        "import_order": 12
    },
    {
        "name": "civic_facilities",
        "display_name": "Civic Facilities",
        "model_name": "CivicFacility",
        "source": "databc",
        "source_type": "WMS",
        "resource_id": "64284a1e-0c89-4ae3-bea4-59bc0eb9d579",
        "permalink_id": "ea7cd54f-1820-4f4a-8b2c-40c8a51f84bd",
        "dataset": "civic-facilities",
        "import_order": 13
    },
    {
        "name": "closed_mills",
        "display_name": "Closed Mills",
        "model_name": "ClosedMill",
        "source": "internal",
        "source_type": "csv",
        "source_file_path": "data/closed_mills.csv",
        "import_order": 100
    },
    {
        "name": "airports",
        "display_name": "Airports",
        "model_name": "Airport",
        "source": "databc",
        "source_type": "WMS",
        "resource_id": "604c8be1-b3f3-45b4-8030-5f9c8be71645",
        "permalink_id": "76b1b7a3-2112-4444-857a-afccf7b20da8",
        "dataset": "bc-airports",
        "import_order": 14
    },
    {
        "name": "hospitals",
        "display_name": "Hospitals",
        "model_name": "Hospital",
        "source": "databc",
        "source_type": "api",
        "resource_id": "5ff82cf4-0448-4063-804a-7321f0f2b4c6",
        "permalink_id": "383eaf98-afd7-436a-9556-67ecf14f64a7",
        "import_order": 35
    },
    {
        "name": "projects",
        "display_name": "Projects",
        "model_name": "Project",
        "source": "other",
        "source_type": "csv",
        "source_file_path": "data/major_projects/",
        "external_url": "https://www2.gov.bc.ca/gov/content/employment-business/economic-development/industry/bc-major-projects-inventory",
        "import_order": 102
    },
    {
        "name": "natural_resource_projects",
        "display_name": "Natural Resource Projects",
        "model_name": "NaturalResourceProject",
        "source": "databc",
        "source_type": "api",
        "resource_id": "2b69cc4b-4076-4272-a5a0-1c731455e063",
        "permalink_id": "5ee75843-06b3-4767-b6c2-3248289f5e8d",
        "import_order": 36
    },
    {
        "name": "economic_projects",
        "display_name": "Economic Projects",
        "model_name": "EconomicProject",
        "source": "databc",
        "source_type": "api",
        "resource_id": "b12cd4cc-b58b-4079-b630-a20b6df58e8d",
        "permalink_id": "ea4c0bdb-a63f-49a4-b14a-09c1560aad0b",
        "import_order": 37
    },
    {
        "name": "servicebc_locations",
        "display_name": "Service BC Office Locations",
        "model_name": "ServiceBCLocation",
        "source": "databc",
        "source_type": "api",
        "resource_id": "c7cc9297-220c-4d6c-a9a7-72d0680b2f74",
        "permalink_id": "2b44d212-5438-47a9-ad23-20eb8ada9709",
        "import_order": 38
    },
    {
        "name": "schools",
        "display_name": "Schools (K-12)",
        "model_name": "School",
        "source": "databc",
        "source_type": "api",
        "resource_id": "5832eff2-3380-435e-911b-5ada41c1d30b",
        "permalink_id": "95da1091-7e8c-4aa6-9c1b-5ab159ea7b42",
        "import_order": 39
    },
    {
        "name": "clinics",
        "display_name": "Walk-in Clinics",
        "model_name": "Clinic",
        "source": "databc",
        "source_type": "api",
        "resource_id": "3ca6b086-c92b-4654-ae82-ff5723d00611",
        "permalink_id": "5e2707c3-0aa4-4d2d-aedc-4dd0914b686a",
        "import_order": 40
    },
    {
        "name": "courts",
        "display_name": "Courts",
        "model_name": "Court",
        "source": "databc",
        "source_type": "api",
        "resource_id": "23aa0b75-2715-4ccb-9a36-9a608450dc2d",
        "permalink_id": "c95a2ad5-f62a-43d6-8678-80a617b6200e",
        "import_order": 41
    },
    {
        "name": "post_secondary_institutions",
        "display_name": "Post-Secondary Institutions",
        "model_name": "PostSecondaryInstitution",
        "source": "databc",
        "source_type": "api",
        "resource_id": "8e4e2a87-2d1d-4931-828e-6327b49f310e",
        "permalink_id": "81558d54-1f96-46c2-94fe-56d26f69c4f5",
        "import_order": 42
    },
    {
        "name": "research_centres",
        "display_name": "Research Centres",
        "model_name": "ResearchCentre",
        "source": "databc",
        "source_type": "api",
        "resource_id": "b930d0c7-31e5-4816-a06d-3ea23dbc7635",
        "permalink_id": "7859ae46-2aa1-47ee-a05b-7d0daa472678",
        "import_order": 43
    },
    {
        "name": "wildfires_zones",
        "display_name": "Wildfire Wildland Urban Interface Risk Class",
        "model_name": "WildfireZone",
        "source": "databc",
        "source_type": "WMS",
        "resource_id": "8eafea9f-3e84-4a9b-bd60-522c0059b74b",
        "permalink_id": "3c71551e-c1aa-4272-9c89-64fbd22a910d",
        "dataset": "bc-wildfire-wildland-urban-interface-risk-class",
        "import_order": 5
    },
    {
        "name": "tsunami_zones",
        "display_name": "Tsunami Notification Zones",
        "model_name": "TsunamiZone",
        "source": "databc",
        "source_type": "WMS",
        "resource_id": "2551b4de-6d79-4ea6-bdb9-a802364208c2",
        "permalink_id": "d9bafe48-5bf7-461b-a8d6-ba6d1e2245f0",
        "dataset": "tsunami-notification-zones-for-bc",
        "import_order": 6
    },
    {
        "name": "municipalities",
        "display_name": "Municipalities",
        "model_name": "Municipality",
        "source": "databc",
        "source_type": "WMS",
        "resource_id": "0bd8e3d1-4d7f-4db8-a8b2-2cd4cd051074",
        "permalink_id": "e3c3c580-996a-4668-8bc5-6aa7c7dc4932",
        "dataset": "municipalities-legally-defined-administrative-areas-of-bc",
        "import_order": 4
    },
    {
        "name": "school_districts",
        "display_name": "School Districts",
        "model_name": "SchoolDistrict",
        "source": "databc",
        "source_type": "WMS",
        "resource_id": "529507c4-d155-4c4d-a499-1a50be41b49d",
        "permalink_id": "78ec5279-4534-49a1-97e8-9d315936f08b",
        "dataset": "school-districts-of-bc",
        "import_order": 7
    },
    {
        "name": "regional_districts",
        "display_name": "Regional Districts",
        "model_name": "RegionalDistrict",
        "source": "databc",
        "source_type": "WMS",
        "resource_id": "eb5a9d9b-fb7b-40aa-a3fe-020993345bbc",
        "permalink_id": "d1aff64e-dbfe-45a6-af97-582b7f6418b9",
        "dataset": "regional-districts-legally-defined-administrative-areas-of-bc",
        "import_order": 8
    },
    {
        "name": "northern_rockies_census_division",
        "display_name": "Northern Rockies Census Division (included as Regional District)",
        "model_name": "RegionalDistrict",
        "source": "databc",
        "source_type": "shp",
        "source_file_path": "data/census_divisions.zip",
        "resource_id": "d7d6e2ea-e742-43ab-94a3-c0eaf48b68de",
        "permalink_id": "ef17918a-597a-4012-8534-f8e71d8735b3",
        "import_order": 102
    },
    {
        "name": "civic_leaders",
        "display_name": "Civic Leaders",
        "model_name": "CivicLeader",
        "source": "internal",
        "source_type": "csv",
        "source_file_path": "data/civicinfo.csv",
        "import_order": 101
    },
    {
        "name": "census",
        "display_name": "Census Subdivisions",
        "model_name": "CensusSubdivision",
        "source": "statscan",
        "source_type": "shp",
        "source_file_path": "data/census.zip",
        "external_url": "https://www12.statcan.gc.ca/census-recensement/2011/geo/bound-limit/bound-limit-2016-eng.cfm",
        "import_order": 1
    },
    {
        "name": "hexes",
        "display_name": "Internet Connectivity (Hexes)",
        "model_name": "Hex",
        "source": "databc",
        "source_type": "shp",
        "source_file_path": "data/hexbc.kml",
        "resource_id": "6b246885-45fb-413f-b8a4-3949729959bc",
        "permalink_id": "ee60bfce-e9ce-449b-ba8f-3491553ede35",
        "dataset": "bc-network-connectivity",
        "import_order": 3
    },
    {
        "name": "services",
        "display_name": "Internet Connectivity (ISPs)",
        "model_name": "Service",
        "source": "openca",
        "source_type": "csv",
        "source_file_path": "data/ISP_Hex_FSI.csv",
        "resource_id": "00a331db-121b-445d-b119-35dbbe3eedd9",
        "sub_resource_id": "ec679621-d333-40c7-a7ea-66e17d007010",
        "external_url": "https://open.canada.ca/data/en/dataset/00a331db-121b-445d-b119-35dbbe3eedd9",
        "import_order": 103
    },
    {
        "name": "roads",
        "display_name": "Roads",
        "model_name": "Road",
        "source": "openca",
        "source_type": "shp",
        "source_file_path": "data/BC_Roads.zip",
        "resource_id": "00a331db-121b-445d-b119-35dbbe3eedd9",
        "sub_resource_id": "4c5d8d60-f9dd-4b80-89ed-0b07205c3026",
        "external_url": "https://open.canada.ca/data/en/dataset/00a331db-121b-445d-b119-35dbbe3eedd9",
        "import_order": 2
    },
    {
        "name": "lakes",
        "display_name": "Lakes",
        "model_name": "Lake",
        "source": "databc",
        "source_type": "WMS",
        "resource_id": null,
        "permalink_id": "cb1e3aba-d3fe-4de1-a2d4-b8b6650fb1f6",
        "dataset": "freshwater-atlas-lakes",
        "import_order": 15
    },
    {
        "name": "rivers",
        "display_name": "Rivers",
        "model_name": "River",
        "source": "databc",
        "source_type": "WMS",
        "resource_id": null,
        "permalink_id": "f7dac054-efbf-402f-ab62-6fc4b32a619e",
        "dataset": "freshwater-atlas-rivers",
        "import_order": 16
    },{
        "name": "port_and_terminal",
        "display_name": "Ports and Terminals",
        "model_name": "PortAndTerminal",
        "source": "databc",
        "source_type": "WMS",
        "resource_id": null,
        "permalink_id": "5f3c273a-7a0d-4b5f-8059-b34cc3f116c7",
        "dataset": "bc-ports-and-terminals",
        "import_order": 17
    },{
        "name": "eao_projects",
        "display_name": "EAO Projects",
        "model_name": "EAOProjects",
        "source": "databc",
        "source_type": "WMS",
        "resource_id": null,
        "permalink_id": "bc1c5380-6fca-4666-996b-049ad8ca04cc",
        "dataset": "environmental-assessment-office-eao-points-svw",
        "import_order": 18
    },{
        "name": "permitted_major_mines",
        "display_name": "Permitted Major Mines",
        "model_name": "PermittedMajorMines",
        "source": "databc",
        "source_type": "WMS",
        "resource_id": null,
        "permalink_id": "01e8a35e-35e3-4b48-93a7-b0d7c9705b62",
        "dataset": "permitted-mine-areas-major-mine",
        "import_order": 19
    },{
        "name": "railways",
        "display_name": "Railways",
        "model_name": "Railway",
        "source": "databc",
        "source_type": "WMS",
        "resource_id": null,
        "permalink_id": "01e8a35e-35e3-4b48-93a7-b0d7c9705b62",
        "dataset": "permitted-mine-areas-major-mine",
        "import_order": 20
    },{
        "name": "laboratory_service",
        "display_name": "Laboratory Service",
        "model_name": "LaboratoryService",
        "source": "databc",
        "source_type": "WMS",
        "resource_id": null,
        "permalink_id": "401671c5-4fc4-4ffb-9e29-0cdc3c9433ba",
        "dataset": "laboratory-services-in-bc",
        "import_order": 21
    },{
        "name": "local_govt_offices",
        "display_name": "Local Government Offices",
        "model_name": "LocalGovernmentOffice",
        "source": "databc",
        "source_type": "WMS",
        "resource_id": null,
        "permalink_id": "0fe8083a-881a-4fa8-8925-3a23b788e1b9",
        "dataset": "local-government-offices",
        "import_order": 22
    },{
        "name": "provincial_electoral_district",
        "display_name": "Provincial Electoral Districts",
        "model_name": "ProvincialElectoralDistrict",
        "source": "databc",
        "source_type": "WMS",
        "resource_id": null,
        "permalink_id": "9530a41d-6484-41e5-b694-acb76e212a58",
        "dataset": "provincial-electoral-districts-electoral-boundaries-redistribution-2015",
        "import_order": 23
    },{
        "name": "health_authority_boundaries",
        "display_name": "Health Authority Boundaries",
        "model_name": "HealthAuthorityBoundary",
        "source": "databc",
        "source_type": "WMS",
        "resource_id": null,
        "permalink_id": "7bc6018f-bb4f-4e5d-845e-c529e3d1ac3b",
        "dataset": "health-authority-boundaries",
        "import_order": 24
    },{
        "name": "census_economic_region",
        "display_name": "Census Economic Regions",
        "model_name": "CensusEconomicRegion",
        "source": "databc",
        "source_type": "WMS",
        "resource_id": null,
        "permalink_id": "1aebc451-a41c-496f-8b18-6f414cde93b7",
        "dataset": "current-census-economic-regions",
        "import_order": 25
    },{
        "name": "natural_resource_regions",
        "display_name": "Natural Resource Regions",
        "model_name": "NaturalResourceRegion",
        "source": "databc",
        "source_type": "WMS",
        "resource_id": null,
        "permalink_id": "dfc492c0-69c5-4c20-a6de-2c9bc999301f",
        "dataset": "natural-resource-nr-regions",
        "import_order": 26
    },{
        "name": "bc_floodplain",
        "display_name": "BC Floodplains",
        "model_name": "BCFloodplain",
        "source": "databc",
        "source_type": "WMS",
        "resource_id": null,
        "permalink_id": "cdf4900e-90c0-449f-beea-43b669bd76a8",
        "dataset": "mapped-floodplains-in-bc-historical",
        "import_order": 27
    },{
        "name": "emergency_social_service_facilities",
        "display_name": "Emergency Social Service Facilities",
        "model_name": "EmergencySocialServiceFacility",
        "source": "databc",
        "source_type": "WMS",
        "resource_id": null,
        "permalink_id": "8473689f-2d06-4e84-ac8b-e91033fd0f0b",
        "dataset": "emergency-social-services-facilities",
        "import_order": 27
    }
    
    
    
]
